genome_automl/__init__.py
genome_automl/app_cli.py
genome_automl/base.py
genome_automl/card.py
genome_automl/datastore.py
genome_automl/estimator.py
genome_automl/evaluationspec.py
genome_automl/evaluationstore.py
genome_automl/evaluationtask.py
genome_automl/explainer.py
genome_automl/meta_extractor.py
genome_automl/modelstore.py
genome_automl/store.py
genome_automl/visualizer.py
genome_automl/cli/__init__.py
genome_automl/cli/app_cli.py
genome_automl/core/__init__.py
genome_automl/core/base_entity.py
genome_automl/core/store.py
genome_automl/datasets/__init__.py
genome_automl/datasets/datastore.py
genome_automl/eli5/__init__.py
genome_automl/eli5/_decision_path.py
genome_automl/eli5/_feature_names.py
genome_automl/eli5/_feature_weights.py
genome_automl/eli5/base.py
genome_automl/eli5/base_utils.py
genome_automl/eli5/explain.py
genome_automl/eli5/gradcam.py
genome_automl/eli5/image.py
genome_automl/eli5/keras.py
genome_automl/eli5/utils.py
genome_automl/eli5/formatters/__init__.py
genome_automl/eli5/formatters/as_dict.py
genome_automl/eli5/formatters/features.py
genome_automl/eli5/lime/__init__.py
genome_automl/eli5/lime/_vectorizer.py
genome_automl/eli5/lime/lime.py
genome_automl/eli5/lime/samplers.py
genome_automl/eli5/lime/textutils.py
genome_automl/eli5/lime/utils.py
genome_automl/eli5/sklearn/__init__.py
genome_automl/eli5/sklearn/_span_analyzers.py
genome_automl/eli5/sklearn/explain_prediction.py
genome_automl/eli5/sklearn/text.py
genome_automl/eli5/sklearn/unhashing.py
genome_automl/eli5/sklearn/utils.py
genome_automl/evaluations/__init__.py
genome_automl/evaluations/card.py
genome_automl/evaluations/evaluationspec.py
genome_automl/evaluations/evaluationstore.py
genome_automl/evaluations/evaluationtask.py
genome_automl/evaluations/cardcomponents/__init__.py
genome_automl/evaluations/cardcomponents/bokeh.py
genome_automl/evaluations/cardcomponents/evidently.py
genome_automl/evaluations/cardcomponents/markdown.py
genome_automl-0.9.41.dist-info/METADATA
genome_automl-0.9.41.dist-info/WHEEL
genome_automl-0.9.41.dist-info/top_level.txt
genome_automl-0.9.41.dist-info/RECORD
